[
    {
        "id": 1,
        "category": "Tech",
        "title": "Tech Summit 2023",
        "date": "2023-05-15",
        "place": "Innovate Tech Center",
        "coverImg": "https://i.ibb.co/zGZHrqL/Blue-Modern-Gaming-Channel-Banner-Landscape.png",
        "speaker": "John Doe",
        "basicPrice": 50,
        "premiumPrice": 100,
        "goldenPrice": 150,
        "details": "Join us for a day of exciting discussions and presentations on the latest in technology.",
        "speakerImg": "https://i.ibb.co/8z08Txm/Saikiran.png",
        "aboutSpeaker": "John Doe is a renowned tech expert with over 15 years of experience in the industry."
      },
      {
        "id": 2,
        "category": "Marketing",
        "title": "Marketing Masterclass",
        "date": "2023-06-20",
        "place": "Grand Convention Center",
        "coverImg": "https://i.ibb.co/CmgZT5d/Cream-Illustrative-Digital-Marketing-Banner.png",
        "speaker": "Jane Smith",
        "basicPrice": 40,
        "premiumPrice": 80,
        "goldenPrice": 120,
        "details": "Learn the latest marketing strategies and techniques from industry experts.",
        "speakerImg": "https://i.ibb.co/3rKbxsy/Anish-Baheti.jpg",
        "aboutSpeaker": "Jane Smith is a seasoned marketing professional known for her innovative and successful campaigns."
      },
      {
        "id": 3,
        "category": "Health",
        "title": "Health and Wellness Expo",
        "date": "2023-08-10",
        "place": "Wellness Center",
        "coverImg": "https://i.ibb.co/KKwDJjY/Viral-Pneumonia-of-The-Lungs-and-Coronavirus-Banner.png",
        "speaker": "Dr. Michael Health",
        "basicPrice": 60,
        "premiumPrice": 120,
        "goldenPrice": 180,
        "details": "Explore the latest trends in health and wellness with expert guidance.",
        "speakerImg": "https://i.ibb.co/6Bsz8N1/Kenny-Sebastian.jpg",
        "aboutSpeaker": "Dr. Michael Health is a leading expert in preventive healthcare and wellness."
      },
      {
        "id": 7,
        "category": "Health",
        "title": "Mindfulness Retreat",
        "date": "2023-11-15",
        "place": "Serene Sanctuary Resort",
        "coverImg": "https://i.ibb.co/pybNbb5/Blue-Green-Illustrative-World-Health-Day-Banner.png",
        "speaker": "Yoga Guru Sarah",
        "basicPrice": 80,
        "premiumPrice": 150,
        "goldenPrice": 220,
        "details": "Immerse yourself in a weekend of mindfulness activities, yoga, and relaxation with renowned instructor Yoga Guru Sarah.",
        "speakerImg": "https://i.ibb.co/6Bsz8N1/Kenny-Sebastian.jpg",
        "aboutSpeaker": "Yoga Guru Sarah has dedicated her life to spreading the benefits of mindfulness and yoga for holistic well-being."
      },
      {
        "id": 8,
        "category": "Tech",
        "title": "AI and Robotics Expo",
        "date": "2023-12-05",
        "place": "Tech Innovations Center",
        "coverImg": "https://i.ibb.co/zGZHrqL/Blue-Modern-Gaming-Channel-Banner-Landscape.png",
        "speaker": "Dr. Alan Robotics",
        "basicPrice": 65,
        "premiumPrice": 120,
        "goldenPrice": 180,
        "details": "Explore the cutting-edge developments in artificial intelligence and robotics with expert Dr. Alan Robotics.",
        "speakerImg": "https://i.ibb.co/QMqChNv/Kunal-Rao.jpg",
        "aboutSpeaker": "Dr. Alan Robotics is a leading researcher in the field of AI and robotics, with numerous contributions to autonomous systems."
      },
      {
        "id": 9,
        "category": "Marketing",
        "title": "Digital Marketing Summit",
        "date": "2024-01-10",
        "place": "Digital Hub Conference Center",
        "coverImg": "https://i.ibb.co/60bcvJL/Blue-Illustrated-Global-Cooperation-Business-Banner.png",
        "speaker": "Marketing Maven Mia",
        "basicPrice": 50,
        "premiumPrice": 90,
        "goldenPrice": 130,
        "details": "Stay ahead in the digital landscape with insights and strategies from the Marketing Maven Mia.",
        "speakerImg": "https://i.ibb.co/3rKbxsy/Anish-Baheti.jpg",
        "aboutSpeaker": "Marketing Maven Mia is a digital marketing expert known for her innovative and impactful online campaigns."
      },
      {
        "id": 10,
        "category": "Music",
        "title": "Jazz and Blues Night",
        "date": "2024-02-20",
        "place": "Harmony Jazz Club",
        "coverImg": "https://i.ibb.co/XStWfnT/White-Blue-Purple-Modern-Live-Music-Banner-Landscape.gif",
        "speaker": "Soulful Saxophonist Sam",
        "basicPrice": 55,
        "premiumPrice": 100,
        "goldenPrice": 150,
        "details": "Experience an enchanting night of jazz and blues with the soulful tunes of Saxophonist Sam.",
        "speakerImg": "https://i.ibb.co/xJQVDVf/arijit-singh.jpg",
        "aboutSpeaker": "Soulful Saxophonist Sam is celebrated for his emotive and expressive performances in the world of jazz."
      },
      {
        "id": 12,
        "category": "Health",
        "title": "Wellness and Nutrition Seminar",
        "date": "2024-04-10",
        "place": "Well-Being Center",
        "coverImg": "https://i.ibb.co/KKwDJjY/Viral-Pneumonia-of-The-Lungs-and-Coronavirus-Banner.png",
        "speaker": "Nutritionist Natalie",
        "basicPrice": 55,
        "premiumPrice": 100,
        "goldenPrice": 150,
        "details": "Learn about the importance of wellness and nutrition for a healthier lifestyle with expert guidance from Nutritionist Natalie.",
        "speakerImg": "https://i.ibb.co/6Bsz8N1/Kenny-Sebastian.jpg",
        "aboutSpeaker": "Nutritionist Natalie is a certified expert in wellness and nutrition, dedicated to promoting a balanced and healthy life."
      },
      {
        "id": 13,
        "category": "Tech",
        "title": "Virtual Reality Summit",
        "date": "2024-05-20",
        "place": "VR Innovation Center",
        "coverImg": "https://i.ibb.co/zGZHrqL/Blue-Modern-Gaming-Channel-Banner-Landscape.png",
        "speaker": "VR Pioneer Victor",
        "basicPrice": 70,
        "premiumPrice": 120,
        "goldenPrice": 180,
        "details": "Explore the latest advancements in virtual reality technology and its applications with VR Pioneer Victor.",
        "speakerImg": "https://i.ibb.co/8z08Txm/Saikiran.png",
        "aboutSpeaker": "VR Pioneer Victor has been at the forefront of virtual reality development, pushing the boundaries of immersive experiences."
      },
      {
        "id": 14,
        "category": "Marketing",
        "title": "Social Media Mastery Workshop",
        "date": "2024-06-15",
        "place": "Digital Marketing Institute",
        "coverImg": "https://i.ibb.co/60bcvJL/Blue-Illustrated-Global-Cooperation-Business-Banner.png",
        "speaker": "Social Media Guru Gary",
        "basicPrice": 40,
        "premiumPrice": 70,
        "goldenPrice": 100,
        "details": "Enhance your social media marketing skills with insights from Social Media Guru Gary and discover strategies for online success.",
        "speakerImg": "https://i.ibb.co/3rKbxsy/Anish-Baheti.jpg",
        "aboutSpeaker": "Social Media Guru Gary is a seasoned expert in social media marketing, with a proven track record of building online communities."
      },
      {
        "id": 15,
        "category": "Music",
        "title": "Rock Concert Extravaganza",
        "date": "2024-07-10",
        "place": "Epic Arena",
        "coverImg": "https://i.ibb.co/chyhtcN/Purple-and-Pink-Illustration-Music-Party-Banner.gif",
        "speaker": "The Rock Legends",
        "basicPrice": 80,
        "premiumPrice": 150,
        "goldenPrice": 220,
        "details": "Get ready for an electrifying night with The Rock Legends, delivering a high-energy rock concert experience.",
        "speakerImg": "https://i.ibb.co/xJQVDVf/arijit-singh.jpg",
        "aboutSpeaker": "The Rock Legends are iconic figures in the world of rock music, known for their legendary performances and timeless hits."
      }
]